odoo/addons/product_packaging_level_purchasable/README.rst
odoo/addons/product_packaging_level_purchasable/__init__.py
odoo/addons/product_packaging_level_purchasable/__manifest__.py
odoo/addons/product_packaging_level_purchasable/i18n/de.po
odoo/addons/product_packaging_level_purchasable/i18n/es.po
odoo/addons/product_packaging_level_purchasable/i18n/fr.po
odoo/addons/product_packaging_level_purchasable/i18n/it.po
odoo/addons/product_packaging_level_purchasable/i18n/product_packaging_level_purchasable.pot
odoo/addons/product_packaging_level_purchasable/models/__init__.py
odoo/addons/product_packaging_level_purchasable/models/product_packaging.py
odoo/addons/product_packaging_level_purchasable/models/product_packaging_level.py
odoo/addons/product_packaging_level_purchasable/models/purchase_order_line.py
odoo/addons/product_packaging_level_purchasable/readme/CONFIGURE.rst
odoo/addons/product_packaging_level_purchasable/readme/CONTRIBUTORS.rst
odoo/addons/product_packaging_level_purchasable/readme/DESCRIPTION.rst
odoo/addons/product_packaging_level_purchasable/static/description/icon.png
odoo/addons/product_packaging_level_purchasable/static/description/index.html
odoo/addons/product_packaging_level_purchasable/tests/__init__.py
odoo/addons/product_packaging_level_purchasable/tests/common.py
odoo/addons/product_packaging_level_purchasable/tests/test_packaging_level_can_be_purchased.py
odoo/addons/product_packaging_level_purchasable/views/product_packaging_level.xml
odoo_addon_product_packaging_level_purchasable-16.0.1.1.0.8.dist-info/METADATA
odoo_addon_product_packaging_level_purchasable-16.0.1.1.0.8.dist-info/WHEEL
odoo_addon_product_packaging_level_purchasable-16.0.1.1.0.8.dist-info/top_level.txt
odoo_addon_product_packaging_level_purchasable-16.0.1.1.0.8.dist-info/RECORD
