Metadata-Version: 2.1
Name: odoo-addon-product_packaging_level_purchasable
Version: 16.0.1.1.0.8
Summary: Control purchase of products via packaging settings.
Home-page: https://github.com/OCA/product-attribute
Author: Camptocamp, BCIM, Odoo Community Association (OCA)
Author-email: support@odoo-community.org
License: AGPL-3
Classifier: Programming Language :: Python
Classifier: Framework :: Odoo
Classifier: Framework :: Odoo :: 16.0
Classifier: License :: OSI Approved :: GNU Affero General Public License v3
Classifier: Development Status :: 3 - Alpha
Requires-Python: >=3.10
Requires-Dist: odoo-addon-product-packaging-level<16.1dev,>=16.0dev
Requires-Dist: odoo<16.1dev,>=16.0a
